MANIFEST.in
README.markdown
setup.py
ckanext/__init__.py
ckanext/deadoralive/__init__.py
ckanext/deadoralive/config.py
ckanext/deadoralive/controllers.py
ckanext/deadoralive/helpers.py
ckanext/deadoralive/plugin.py
ckanext/deadoralive/2.2_templates/package/resource_read.html
ckanext/deadoralive/logic/__init__.py
ckanext/deadoralive/logic/action/__init__.py
ckanext/deadoralive/logic/action/get.py
ckanext/deadoralive/logic/action/update.py
ckanext/deadoralive/logic/auth/__init__.py
ckanext/deadoralive/logic/auth/get.py
ckanext/deadoralive/logic/auth/update.py
ckanext/deadoralive/model/__init__.py
ckanext/deadoralive/model/results.py
ckanext/deadoralive/templates/broken_links_by_email.html
ckanext/deadoralive/templates/broken_links_by_organization.html
ckanext/deadoralive/templates/footer.html
ckanext/deadoralive/templates/admin/base.html
ckanext/deadoralive/templates/package/resource_read.html
ckanext/deadoralive/templates/package/snippets/resource_item.html
ckanext/deadoralive/templates/snippets/deadoralive_resource_result.html
ckanext/deadoralive/tests/__init__.py
ckanext/deadoralive/tests/factories.py
ckanext/deadoralive/tests/helpers.py
ckanext/deadoralive/tests/test_config.py
ckanext/deadoralive/tests/test_controllers.py
ckanext/deadoralive/tests/test_plugin.py
ckanext/deadoralive/tests/logic/__init__.py
ckanext/deadoralive/tests/logic/action/__init__.py
ckanext/deadoralive/tests/logic/action/test_get.py
ckanext/deadoralive/tests/logic/action/test_update.py
ckanext/deadoralive/tests/logic/auth/__init__.py
ckanext/deadoralive/tests/logic/auth/test_get.py
ckanext/deadoralive/tests/logic/auth/test_update.py
ckanext/deadoralive/tests/model/__init__.py
ckanext/deadoralive/tests/model/test_results.py
ckanext/deadoralive/theme/bower.json
ckanext/deadoralive/theme/gulpfile.js
ckanext/deadoralive/theme/package.json
ckanext/deadoralive/theme/assets/less/master.less
ckanext/deadoralive/theme/resources/styles/master.css
ckanext_deadoralive.egg-info/PKG-INFO
ckanext_deadoralive.egg-info/SOURCES.txt
ckanext_deadoralive.egg-info/dependency_links.txt
ckanext_deadoralive.egg-info/entry_points.txt
ckanext_deadoralive.egg-info/top_level.txt