Metadata-Version: 1.1
Name: ckanext-deadoralive
Version: 0.1.4
Summary: A CKAN extension for the Dead or Alive link checker service
Home-page: https://github.com/ckan/ckanext-deadoralive
Author: Sean Hammond
Author-email: deadoralive@seanh.cc
License: AGPL
Keywords: ckan
Platform: UNKNOWN
Classifier: Development Status :: 4 - Beta
Classifier: Intended Audience :: Other Audience
Classifier: Topic :: Internet :: WWW/HTTP :: Site Management :: Link Checking
Classifier: License :: OSI Approved :: GNU Affero General Public License v3 or later (AGPLv3+)
Classifier: Programming Language :: Python :: 2.7
